CrackingCodesWithPythonZhongwenban/README.md
CrackingCodesWithPythonZhongwenban/__init__.py
CrackingCodesWithPythonZhongwenban/__main__.py
CrackingCodesWithPythonZhongwenban/file.epub
CrackingCodesWithPythonZhongwenban/index.html
CrackingCodesWithPythonZhongwenban/css/__init__.py
CrackingCodesWithPythonZhongwenban/css/annotations.css
CrackingCodesWithPythonZhongwenban/css/main.css
CrackingCodesWithPythonZhongwenban/css/normalize.css
CrackingCodesWithPythonZhongwenban/css/popup.css
CrackingCodesWithPythonZhongwenban/font/__init__.py
CrackingCodesWithPythonZhongwenban/font/fontello.eot
CrackingCodesWithPythonZhongwenban/font/fontello.svg
CrackingCodesWithPythonZhongwenban/font/fontello.ttf
CrackingCodesWithPythonZhongwenban/font/fontello.woff
CrackingCodesWithPythonZhongwenban/img/__init__.py
CrackingCodesWithPythonZhongwenban/img/annotator-glyph-sprite.png
CrackingCodesWithPythonZhongwenban/img/annotator-icon-sprite.png
CrackingCodesWithPythonZhongwenban/img/apple-touch-icon.png
CrackingCodesWithPythonZhongwenban/img/cancelfullscreen.png
CrackingCodesWithPythonZhongwenban/img/close.png
CrackingCodesWithPythonZhongwenban/img/fullscreen.png
CrackingCodesWithPythonZhongwenban/img/loader.gif
CrackingCodesWithPythonZhongwenban/img/menu-icon.png
CrackingCodesWithPythonZhongwenban/img/save.png
CrackingCodesWithPythonZhongwenban/img/saved.png
CrackingCodesWithPythonZhongwenban/img/settings-s.png
CrackingCodesWithPythonZhongwenban/img/settings.png
CrackingCodesWithPythonZhongwenban/img/star.png
CrackingCodesWithPythonZhongwenban/js/__init__.py
CrackingCodesWithPythonZhongwenban/js/epub.js
CrackingCodesWithPythonZhongwenban/js/epub.min.js
CrackingCodesWithPythonZhongwenban/js/epub.min.map
CrackingCodesWithPythonZhongwenban/js/hooks.min.js
CrackingCodesWithPythonZhongwenban/js/hooks.min.map
CrackingCodesWithPythonZhongwenban/js/reader.js
CrackingCodesWithPythonZhongwenban/js/reader.js.map
CrackingCodesWithPythonZhongwenban/js/reader.min.js
cracking_codes_with_python_zhongwenban-2024.3.5.0.dist-info/METADATA
cracking_codes_with_python_zhongwenban-2024.3.5.0.dist-info/WHEEL
cracking_codes_with_python_zhongwenban-2024.3.5.0.dist-info/entry_points.txt
cracking_codes_with_python_zhongwenban-2024.3.5.0.dist-info/top_level.txt
cracking_codes_with_python_zhongwenban-2024.3.5.0.dist-info/RECORD
